.DS_Store
wagtailimportexport/__init__.py
wagtailimportexport/admin_urls.py
wagtailimportexport/apps.py
wagtailimportexport/config.py
wagtailimportexport/exporting.py
wagtailimportexport/forms.py
wagtailimportexport/functions.py
wagtailimportexport/importing.py
wagtailimportexport/views.py
wagtailimportexport/wagtail_hooks.py
wagtailimportexport/migrations/__init__.py
wagtailimportexport/templates/wagtailimportexport/export-page.html
wagtailimportexport/templates/wagtailimportexport/import-page.html
wagtailimportexport/templates/wagtailimportexport/index.html
wagtailimportexport/tests/__init__.py
wagtailimportexport/tests/test_functions.py
wagtail_import_export_tool-0.9.5.dist-info/LICENSE
wagtail_import_export_tool-0.9.5.dist-info/METADATA
wagtail_import_export_tool-0.9.5.dist-info/WHEEL
wagtail_import_export_tool-0.9.5.dist-info/top_level.txt
wagtail_import_export_tool-0.9.5.dist-info/RECORD
