Metadata-Version: 2.1
Name: wagtail-import-export-tool
Version: 0.9.5
Summary: Import/Export tool for Wagtail CMS (built on top of Django), that supports pages, images, documents, and snippets.
Home-page: https://github.com/berkalpyakici/wagtail-import-export-tool
Author: Berk Alp Yakici
Author-email: contact@berkalpyakici.com
License: UNKNOWN
Platform: UNKNOWN
Classifier: Operating System :: OS Independent
Classifier: Environment :: Web Environment
Classifier: Intended Audience :: Developers
Classifier: License :: OSI Approved :: BSD License
Classifier: Programming Language :: Python
Classifier: Programming Language :: Python :: 3
Classifier: Framework :: Django
